[
  {
    "ref": "context-Kerner_616_front", 
    "capacity": 64, 
    "type": "context", 
    "name": "616 Kerner", 
    "mods": [
      {
        "town_dir": LEFT, 
        "neighbors": [
          "context-Kerner_716_front", 
          "", 
          "context-Kerner_cross", 
          "context-Kerner_616_interior"
        ], 
        "realm": "Streets",
        "orientation": 0, 
        "nitty_bits": 3, 
        "port_dir": LEFT, 
        "type": "Region"
      }
    ]
  }, 
  {
    "ref": "item-Ground.63a6.Kerner_616_front", 
    "mods": [
      {
        "y": 4, 
        "x": 0, 
        "style": 1, 
        "type": "Ground", 
        "orientation": 220
      }
    ], 
    "type": "item", 
    "name": "Ground", 
    "in": "context-Kerner_616_front"
  }, 
  {
    "ref": "item-Wall.0e83.Kerner_616_front", 
    "mods": [
      {
        "y": 0, 
        "x": 0, 
        "style": 4, 
        "type": "Wall", 
        "orientation": 164
      }
    ], 
    "type": "item", 
    "name": "Wall", 
    "in": "context-Kerner_616_front"
  }, 
  {
    "ref": "item-Wall.036c.Kerner_616_front", 
    "mods": [
      {
        "y": 2, 
        "x": 0, 
        "style": 7, 
        "type": "Wall", 
        "orientation": 188
      }
    ], 
    "type": "item", 
    "name": "Wall", 
    "in": "context-Kerner_616_front"
  }, 
  {
    "ref": "item-Building.159f.Kerner_616_front", 
    "mods": [
      {
        "y": 32, 
        "x": 72, 
        "connection": "context-Kerner_616_interior", 
        "type": "Building", 
        "orientation": 33
      }
    ], 
    "type": "item", 
    "name": "Building", 
    "in": "context-Kerner_616_front"
  }, 
  {
    "ref": "item-Plant.6c85.Kerner_616_front", 
    "mods": [
      {
        "style": 1, 
        "orientation": 32, 
        "mass": 1, 
        "y": 33, 
        "x": 60, 
        "type": "Plant"
      }
    ], 
    "type": "item", 
    "name": "Plant", 
    "in": "context-Kerner_616_front"
  }, 
  {
    "ref": "item-Plant.41cc.Kerner_616_front", 
    "mods": [
      {
        "style": 1, 
        "orientation": 49, 
        "mass": 1, 
        "y": 33, 
        "x": 48, 
        "type": "Plant"
      }
    ], 
    "type": "item", 
    "name": "Plant", 
    "in": "context-Kerner_616_front"
  }, 
  {
    "ref": "item-Mailbox.5ca3.Kerner_616_front", 
    "mods": [
      {
        "y": 155, 
        "x": 124, 
        "type": "Mailbox", 
        "orientation": 32
      }
    ], 
    "type": "item", 
    "name": "Mailbox", 
    "in": "context-Kerner_616_front"
  }, 
  {
    "ref": "item-Sign.1e49.Kerner_616_front", 
    "mods": [
      {
        "style": 5, 
        "orientation": 16, 
        "ascii": [
          32, 
          32, 
          32, 
          54, 
          49, 
          54, 
          32, 
          32, 
          32, 
          32, 
          32, 
          32, 
          32, 
          32, 
          32, 
          32, 
          32, 
          32, 
          32, 
          32, 
          32, 
          32, 
          32, 
          32, 
          32, 
          32, 
          32, 
          32, 
          32, 
          32, 
          32, 
          32, 
          32, 
          32, 
          32, 
          32, 
          32, 
          32, 
          32, 
          32
        ], 
        "gr_state": 8, 
        "y": 32, 
        "x": 124, 
        "type": "Sign"
      }
    ], 
    "type": "item", 
    "name": "Sign", 
    "in": "context-Kerner_616_front"
  }, 
  {
    "ref": "item-Plant.5214.Kerner_616_front", 
    "mods": [
      {
        "style": 1, 
        "orientation": 33, 
        "mass": 1, 
        "y": 33, 
        "x": 84, 
        "type": "Plant"
      }
    ], 
    "type": "item", 
    "name": "Plant", 
    "in": "context-Kerner_616_front"
  }, 
  {
    "ref": "item-Plant.9956.Kerner_616_front", 
    "mods": [
      {
        "style": 1, 
        "orientation": 32, 
        "mass": 1, 
        "y": 33, 
        "x": 24, 
        "type": "Plant"
      }
    ], 
    "type": "item", 
    "name": "Plant", 
    "in": "context-Kerner_616_front"
  }, 
  {
    "ref": "item-Plant.f538.Kerner_616_front", 
    "mods": [
      {
        "style": 1, 
        "orientation": 33, 
        "mass": 1, 
        "y": 33, 
        "x": 12, 
        "type": "Plant"
      }
    ], 
    "type": "item", 
    "name": "Plant", 
    "in": "context-Kerner_616_front"
  }, 
  {
    "ref": "item-Street.1b14.Kerner_616_front", 
    "mods": [
      {
        "y": 10, 
        "x": 68, 
        "type": "Street", 
        "orientation": 112, 
        "gr_state": 6
      }
    ], 
    "type": "item", 
    "name": "Street", 
    "in": "context-Kerner_616_front"
  }
]