[
  {
    "ref": "context-Kerner_216_interior", 
    "capacity": 64, 
    "type": "context", 
    "name": "216 Kerner", 
    "mods": [
      {
        "town_dir": UP, 
        "neighbors": [
          "", 
          "context-Kerner_216_front", 
          "", 
          ""
        ], 
        "realm": "Streets",
        "orientation": 2, 
        "nitty_bits": 3, 
        "port_dir": UP, 
        "type": "Region"
      }
    ]
  }, 
  {
    "ref": "item-Ground.3189.Kerner_216_interior", 
    "mods": [
      {
        "y": 4, 
        "x": 0, 
        "style": 1, 
        "type": "Ground", 
        "orientation": 16
      }
    ], 
    "type": "item", 
    "name": "Ground", 
    "in": "context-Kerner_216_interior"
  }, 
  {
    "ref": "item-Wall.145d.Kerner_216_interior", 
    "mods": [
      {
        "y": 0, 
        "x": 0, 
        "style": 4, 
        "type": "Wall", 
        "orientation": 80
      }
    ], 
    "type": "item", 
    "name": "Wall", 
    "in": "context-Kerner_216_interior"
  }, 
  {
    "ref": "item-Table.11c6.Kerner_216_interior", 
    "mods": [
      {
        "orientation": 0, 
        "key_lo": 0, 
        "key_hi": 0, 
        "y": 129, 
        "x": 56, 
        "type": "Table", 
        "open_flags": 3
      }
    ], 
    "type": "item", 
    "name": "Table", 
    "in": "context-Kerner_216_interior"
  }, 
  {
    "ref": "item-Chest.cb48.Kerner_216_interior", 
    "mods": [
      {
        "orientation": 236, 
        "key_lo": 0, 
        "key_hi": 0, 
        "y": 32, 
        "x": 8, 
        "type": "Chest", 
        "open_flags": 2
      }
    ], 
    "type": "item", 
    "name": "Chest", 
    "in": "context-Kerner_216_interior"
  }, 
  {
    "ref": "item-Chair.e28e.Kerner_216_interior", 
    "mods": [
      {
        "y": 138, 
        "x": 44, 
        "type": "Chair", 
        "orientation": 204
      }
    ], 
    "type": "item", 
    "name": "Chair", 
    "in": "context-Kerner_216_interior"
  }, 
  {
    "ref": "item-Door.e969.Kerner_216_interior", 
    "mods": [
      {
        "orientation": 16, 
        "key_lo": 0, 
        "connection": "context-Kerner_216_front", 
        "key_hi": 0, 
        "y": 33, 
        "x": 120, 
        "type": "Door", 
        "open_flags": 2
      }
    ], 
    "type": "item", 
    "name": "Door", 
    "in": "context-Kerner_216_interior"
  }, 
  {
    "ref": "item-Floor_lamp.0103.Kerner_216_interior", 
    "mods": [
      {
        "y": 31, 
        "x": 72, 
        "type": "Floor_lamp", 
        "orientation": 172
      }
    ], 
    "type": "item", 
    "name": "Floor_lamp", 
    "in": "context-Kerner_216_interior"
  }, 
  {
    "ref": "item-Chair.fc4d.Kerner_216_interior", 
    "mods": [
      {
        "y": 138, 
        "x": 88, 
        "type": "Chair", 
        "orientation": 204
      }
    ], 
    "type": "item", 
    "name": "Chair", 
    "in": "context-Kerner_216_interior"
  }
]