[
  {
    "ref": "context-Desert_5f", 
    "capacity": 64, 
    "type": "context", 
    "name": "The Desert", 
    "mods": [
      {
        "town_dir": "", 
        "neighbors": [
          "", 
          "", 
          "", 
          "context-Desert_4f"
        ], 
        "orientation": 0, 
        "nitty_bits": 3, 
        "port_dir": "", 
        "type": "Region"
      }
    ]
  }, 
  {
    "ref": "item-Sky.bc1e.Desert_5f", 
    "mods": [
      {
        "y": 0, 
        "x": 0, 
        "style": 4, 
        "type": "Sky", 
        "orientation": 244
      }
    ], 
    "type": "item", 
    "name": "Sky", 
    "in": "context-Desert_5f"
  }, 
  {
    "ref": "item-Flat.92f0.Desert_5f", 
    "mods": [
      {
        "y": 4, 
        "x": 0, 
        "type": "Flat", 
        "orientation": 188, 
        "flat_type": 0
      }
    ], 
    "type": "item", 
    "name": "Flat", 
    "in": "context-Desert_5f"
  }, 
  {
    "ref": "item-Flat.8bf4.Desert_5f", 
    "mods": [
      {
        "flat_type": 2, 
        "style": 1, 
        "orientation": 188, 
        "y": 4, 
        "x": 0, 
        "type": "Flat"
      }
    ], 
    "type": "item", 
    "name": "Flat", 
    "in": "context-Desert_5f"
  }
]