[
  {
    "ref": "context-Woods_7c", 
    "capacity": 6, 
    "type": "context", 
    "name": "Woods_7c - Generated by Regionator", 
    "mods": [
      {
        "town_dir": "", 
        "port_dir": "", 
        "type": "Region", 
        "neighbors": [
          "context-Woods_7d", 
          "context-Woods_7b", 
          "context-Woods_6c", 
          "context-Woods_7d"
        ], 
        "nitty_bits": 3
      }
    ]
  }, 
  {
    "ref": "item-groundd6bd.context-Woods_7c", 
    "mods": [
      {
        "y": 4, 
        "x": 0, 
        "type": "Ground", 
        "orientation": 204
      }
    ], 
    "type": "item", 
    "name": "Ground", 
    "in": "context-Woods_7c"
  }, 
  {
    "ref": "item-sky0a26.context-Woods_7c", 
    "mods": [
      {
        "y": 0, 
        "x": 0, 
        "style": 4, 
        "type": "Sky", 
        "orientation": 0
      }
    ], 
    "type": "item", 
    "name": "Sky", 
    "in": "context-Woods_7c"
  }, 
  {
    "ref": "item-tree59dc.context-Woods_7c", 
    "mods": [
      {
        "y": 33, 
        "x": 88, 
        "type": "Tree", 
        "orientation": 236, 
        "gr_state": 1
      }
    ], 
    "type": "item", 
    "name": "Tree", 
    "in": "context-Woods_7c"
  }, 
  {
    "ref": "item-rock1e35.context-Woods_7c", 
    "mods": [
      {
        "y": 138, 
        "x": 8, 
        "mass": 1, 
        "type": "Rock", 
        "orientation": 32
      }
    ], 
    "type": "item", 
    "name": "Rock", 
    "in": "context-Woods_7c"
  }, 
  {
    "ref": "item-tree5234.context-Woods_7c", 
    "mods": [
      {
        "y": 35, 
        "x": 40, 
        "type": "Tree", 
        "orientation": 172
      }
    ], 
    "type": "item", 
    "name": "Tree", 
    "in": "context-Woods_7c"
  }, 
  {
    "ref": "item-treebd58.context-Woods_7c", 
    "mods": [
      {
        "y": 57, 
        "x": 88, 
        "type": "Tree", 
        "orientation": 188, 
        "gr_state": 3
      }
    ], 
    "type": "item", 
    "name": "Tree", 
    "in": "context-Woods_7c"
  }, 
  {
    "ref": "item-tree7a05.context-Woods_7c", 
    "mods": [
      {
        "y": 57, 
        "x": 84, 
        "type": "Tree", 
        "orientation": 189, 
        "gr_state": 3
      }
    ], 
    "type": "item", 
    "name": "Tree", 
    "in": "context-Woods_7c"
  }, 
  {
    "ref": "item-tree7138.context-Woods_7c", 
    "mods": [
      {
        "y": 33, 
        "x": 128, 
        "type": "Tree", 
        "orientation": 220, 
        "gr_state": 1
      }
    ], 
    "type": "item", 
    "name": "Tree", 
    "in": "context-Woods_7c"
  }, 
  {
    "ref": "item-tree86b5.context-Woods_7c", 
    "mods": [
      {
        "y": 75, 
        "x": 44, 
        "type": "Tree", 
        "orientation": 172, 
        "gr_state": 3
      }
    ], 
    "type": "item", 
    "name": "Tree", 
    "in": "context-Woods_7c"
  }, 
  {
    "ref": "item-tree937e.context-Woods_7c", 
    "mods": [
      {
        "y": 141, 
        "x": 20, 
        "type": "Tree", 
        "orientation": 16
      }
    ], 
    "type": "item", 
    "name": "Tree", 
    "in": "context-Woods_7c"
  }, 
  {
    "ref": "item-tree1bda.context-Woods_7c", 
    "mods": [
      {
        "y": 71, 
        "x": 36, 
        "type": "Tree", 
        "orientation": 173, 
        "gr_state": 3
      }
    ], 
    "type": "item", 
    "name": "Tree", 
    "in": "context-Woods_7c"
  }, 
  {
    "ref": "item-bushcef7.context-Woods_7c", 
    "mods": [
      {
        "y": 138, 
        "x": 44, 
        "type": "Bush", 
        "orientation": 40
      }
    ], 
    "type": "item", 
    "name": "Bush", 
    "in": "context-Woods_7c"
  }, 
  {
    "ref": "item-bush6712.context-Woods_7c", 
    "mods": [
      {
        "y": 136, 
        "x": 68, 
        "type": "Bush", 
        "orientation": 64
      }
    ], 
    "type": "item", 
    "name": "Bush", 
    "in": "context-Woods_7c"
  }, 
  {
    "ref": "item-bushd2cf.context-Woods_7c", 
    "mods": [
      {
        "y": 146, 
        "x": 136, 
        "type": "Bush", 
        "orientation": 80
      }
    ], 
    "type": "item", 
    "name": "Bush", 
    "in": "context-Woods_7c"
  }, 
  {
    "ref": "item-plant3d8f.context-Woods_7c", 
    "mods": [
      {
        "style": 2, 
        "orientation": 32, 
        "mass": 1, 
        "y": 148, 
        "x": 4, 
        "type": "Plant"
      }
    ], 
    "type": "item", 
    "name": "Plant", 
    "in": "context-Woods_7c"
  }, 
  {
    "ref": "item-plant1446.context-Woods_7c", 
    "mods": [
      {
        "style": 2, 
        "orientation": 32, 
        "mass": 1, 
        "y": 145, 
        "x": 80, 
        "type": "Plant"
      }
    ], 
    "type": "item", 
    "name": "Plant", 
    "in": "context-Woods_7c"
  }, 
  {
    "ref": "item-plantbafb.context-Woods_7c", 
    "mods": [
      {
        "style": 2, 
        "orientation": 33, 
        "mass": 1, 
        "y": 135, 
        "x": 100, 
        "type": "Plant"
      }
    ], 
    "type": "item", 
    "name": "Plant", 
    "in": "context-Woods_7c"
  }, 
  {
    "ref": "item-tree3e6a.context-Woods_7c", 
    "mods": [
      {
        "y": 65, 
        "x": 128, 
        "type": "Tree", 
        "orientation": 220, 
        "gr_state": 3
      }
    ], 
    "type": "item", 
    "name": "Tree", 
    "in": "context-Woods_7c"
  }, 
  {
    "ref": "item-tree9f8d.context-Woods_7c", 
    "mods": [
      {
        "y": 66, 
        "x": 128, 
        "type": "Tree", 
        "orientation": 221, 
        "gr_state": 3
      }
    ], 
    "type": "item", 
    "name": "Tree", 
    "in": "context-Woods_7c"
  }, 
  {
    "ref": "item-bush0e5c.context-Woods_7c", 
    "mods": [
      {
        "y": 138, 
        "x": 104, 
        "style": 4, 
        "type": "Bush", 
        "orientation": 9
      }
    ], 
    "type": "item", 
    "name": "Bush", 
    "in": "context-Woods_7c"
  }
]